contextcounter/__init__.py
contextcounter/analytics.py
contextcounter/counter.py
contextcounter/providers.py
contextcounter-0.1.8.dist-info/METADATA
contextcounter-0.1.8.dist-info/WHEEL
contextcounter-0.1.8.dist-info/licenses/LICENSE
contextcounter-0.1.8.dist-info/RECORD
