Metadata-Version: 2.4
Name: contextcounter
Version: 0.1.8
Summary: Universal context limits, token counting and tool callings for OpenAI, Anthropic, and Gemini.
Author: Nemlig ADK
License: MIT
License-File: LICENSE
Requires-Python: >=3.9
Provides-Extra: anthropic
Requires-Dist: anthropic>=0.34.0; extra == 'anthropic'
Provides-Extra: openai
Requires-Dist: openai>=1.40.0; extra == 'openai'
Requires-Dist: tiktoken>=0.6.0; extra == 'openai'
Provides-Extra: tokenizers
Requires-Dist: tiktoken>=0.6.0; extra == 'tokenizers'
Requires-Dist: transformers>=4.42.0; extra == 'tokenizers'
